Metadata-Version: 2.1
Name: distributions-jaaf
Version: 1.3
Summary: Gaussian distributions JAAF
